bases/__init__.py
bases/py.typed
bases/random.py
bases/alphabet/__init__.py
bases/alphabet/abstract.py
bases/alphabet/range_alphabet.py
bases/alphabet/string_alphabet.py
bases/encoding/__init__.py
bases/encoding/base.py
bases/encoding/block.py
bases/encoding/errors.py
bases/encoding/fixchar.py
bases/encoding/simple.py
bases/encoding/zeropad.py
makkus.bases-0.2.4.dist-info/LICENSE
makkus.bases-0.2.4.dist-info/METADATA
makkus.bases-0.2.4.dist-info/WHEEL
makkus.bases-0.2.4.dist-info/top_level.txt
makkus.bases-0.2.4.dist-info/RECORD
