Metadata-Version: 2.1
Name: makkus.bases
Version: 0.2.4
Summary: Forked from the original author until they incorporate latest fixes; Python library for general Base-N encodings.
Home-page: https://github.com/hashberg-io/bases
Author: hashberg
Author-email: sg495@users.noreply.github.com
Project-URL: Bug Tracker, https://github.com/hashberg-io/bases/issues
Classifier: Development Status :: 4 - Beta
Classifier: Programming Language :: Python :: 3.12
Classifier: Programming Language :: Python :: 3.11
Classifier: Programming Language :: Python :: 3.10
Classifier: Programming Language :: Python :: 3.9
Classifier: Programming Language :: Python :: 3.8
Classifier: Operating System :: OS Independent
Classifier: Natural Language :: English
Classifier: Typing :: Typed
Requires-Python: >=3.7
License-File: LICENSE
Requires-Dist: typing-extensions
Requires-Dist: makkus.typing-validation ==1.0.3
Provides-Extra: dev
Requires-Dist: mypy ; extra == 'dev'
Requires-Dist: pylint ; extra == 'dev'
Requires-Dist: pytest ; extra == 'dev'
Requires-Dist: pytest-cov ; extra == 'dev'
Requires-Dist: base58 ; extra == 'dev'
